kasane/__init__.py
kasane/cmd.py
kasane/ops/__init__.py
kasane/ops/apply.py
kasane/ops/common.py
kasane/ops/jsonnet.py
kasane/ops/show.py
kasane/ops/update.py
kasane-0.1.4.dist-info/LICENSE
kasane-0.1.4.dist-info/METADATA
kasane-0.1.4.dist-info/WHEEL
kasane-0.1.4.dist-info/entry_points.txt
kasane-0.1.4.dist-info/top_level.txt
kasane-0.1.4.dist-info/RECORD
