Metadata-Version: 2.1
Name: kasane
Version: 0.1.4
Summary: A simple kubernets deployment manager
Home-page: https://github.com/google/kasane
Author: Vladimir Pouzanov
Author-email: farcaller@gmail.com
License: Apache-2
Keywords: kubernetes helm package-manager docker jsonnet
Platform: UNKNOWN
Requires-Dist: click
Requires-Dist: ruamel.yaml
Requires-Dist: requests
Requires-Dist: jinja2
Requires-Dist: jsonnet
